Metadata-Version: 2.1
Name: mckomcko
Version: 0.0
Summary: Gaussian and Binomial distributions
Author-email: evstabpro@gmail.com
License: UNKNOWN
Platform: UNKNOWN
